obsidianki/__init__.py
obsidianki/main.py
obsidianki/ai/__init__.py
obsidianki/ai/call.py
obsidianki/ai/client.py
obsidianki/ai/models.py
obsidianki/ai/prompts.py
obsidianki/ai/tools.py
obsidianki/ai/vectors.py
obsidianki/api/__init__.py
obsidianki/api/anki.py
obsidianki/api/base.py
obsidianki/api/obsidian.py
obsidianki/cli/__init__.py
obsidianki/cli/config.py
obsidianki/cli/help_utils.py
obsidianki/cli/models.py
obsidianki/cli/processors.py
obsidianki/cli/services.py
obsidianki/cli/utils.py
obsidianki/cli/wizard.py
obsidianki/cli/commands/__init__.py
obsidianki/cli/commands/config_cmd.py
obsidianki/cli/commands/deck_cmd.py
obsidianki/cli/commands/edit_cmd.py
obsidianki/cli/commands/hide_cmd.py
obsidianki/cli/commands/history_cmd.py
obsidianki/cli/commands/tag_cmd.py
obsidianki/cli/commands/template_cmd.py
obsidianki/cli/commands/vector_cmd.py
obsidianki/cli/interactive/__init__.py
obsidianki/cli/interactive/approval.py
obsidianki/cli/interactive/card_selector.py
obsidianki/cli/interactive/edit_mode.py
obsidianki-0.9.0.dist-info/METADATA
obsidianki-0.9.0.dist-info/WHEEL
obsidianki-0.9.0.dist-info/entry_points.txt
obsidianki-0.9.0.dist-info/top_level.txt
obsidianki-0.9.0.dist-info/RECORD
