Metadata-Version: 2.4
Name: obsidianki
Version: 0.9.0
Summary: Generate flashcards from Obsidian notes using AI and sync them to Anki
Author-email: ccmdi <ccmdi.dev@gmail.com>
License: MIT
Project-URL: Homepage, https://github.com/ccmdi/obsidianki
Project-URL: Repository, https://github.com/ccmdi/obsidianki
Project-URL: Issues, https://github.com/ccmdi/obsidianki/issues
Requires-Python: >=3.8
Requires-Dist: requests>=2.25.0
Requires-Dist: python-dotenv>=0.19.0
Requires-Dist: rich>=13.0.0
Requires-Dist: urllib3>=1.26.0
Requires-Dist: pygments>=2.10.0
Requires-Dist: questionary>=2.0.0
Requires-Dist: httpx>=0.24.0
Provides-Extra: dev
Requires-Dist: pytest>=7.0.0; extra == "dev"
Requires-Dist: pytest-mock>=3.10.0; extra == "dev"
